pysh/__init__.py
pysh/py.typed
pysh-3.3.1.dist-info/WHEEL
pysh-3.3.1.dist-info/METADATA
pysh-3.3.1.dist-info/RECORD
